<?xml version="1.0" encoding="utf-8" ?><dwsync><file name="B2090101v.mp3" server="siteground343.com/public_html/qasid.com/commons/" local="3608863350" remote="3602731980" Dst="-1" /><file name="B2090102v.mp3" server="siteground343.com/public_html/qasid.com/commons/" local="3608863350" remote="3602731980" Dst="-1" /><file name="B2090103v.mp3" server="siteground343.com/public_html/qasid.com/commons/" local="3608863351" remote="3602731980" Dst="-1" /><file name="B2090104v.mp3" server="siteground343.com/public_html/qasid.com/commons/" local="3608863351" remote="3602731980" Dst="-1" /><file name="B2090105v.mp3" server="siteground343.com/public_html/qasid.com/commons/" local="3608863351" remote="3602731980" Dst="-1" /><file name="B2090106v.mp3" server="siteground343.com/public_html/qasid.com/commons/" local="3608863352" remote="3602731980" Dst="-1" /><file name="B2090107v.mp3" server="siteground343.com/public_html/qasid.com/commons/" local="3608863352" remote="3602731980" Dst="-1" /><file name="B2090108v.mp3" server="siteground343.com/public_html/qasid.com/commons/" local="3608863352" remote="3602731980" Dst="-1" /><file name="B2090109v.mp3" server="siteground343.com/public_html/qasid.com/commons/" local="3608863353" remote="3602731980" Dst="-1" /><file name="B2090110v.mp3" server="siteground343.com/public_html/qasid.com/commons/" local="3608863353" remote="3602731980" Dst="-1" /><file name="B2090111v.mp3" server="siteground343.com/public_html/qasid.com/commons/" local="3608863353" remote="3602731980" Dst="-1" /><file name="B2090112v.mp3" server="siteground343.com/public_html/qasid.com/commons/" local="3608863354" remote="3602731980" Dst="-1" /><file name="B2090113v.mp3" server="siteground343.com/public_html/qasid.com/commons/" local="3608863354" remote="3602731980" Dst="-1" /><file name="B2090114v.mp3" server="siteground343.com/public_html/qasid.com/commons/" local="3608863355" remote="3602731980" Dst="-1" /><file name="B2090115v.mp3" server="siteground343.com/public_html/qasid.com/commons/" local="3608863355" remote="3602731980" Dst="-1" /><file name="B2090116v.mp3" server="siteground343.com/public_html/qasid.com/commons/" local="3608863355" remote="3602731980" Dst="-1" /><file name="B2090117v.mp3" server="siteground343.com/public_html/qasid.com/commons/" local="3608863356" remote="3602731980" Dst="-1" /><file name="B2090118v.mp3" server="siteground343.com/public_html/qasid.com/commons/" local="3608863356" remote="3602731980" Dst="-1" /><file name="B2090119v.mp3" server="siteground343.com/public_html/qasid.com/commons/" local="3608863356" remote="3602731980" Dst="-1" /><file name="B2090120v.mp3" server="siteground343.com/public_html/qasid.com/commons/" local="3608863357" remote="3602731980" Dst="-1" /><file name="B2090121v.mp3" server="siteground343.com/public_html/qasid.com/commons/" local="3608863357" remote="3602731980" Dst="-1" /><file name="B2090122v.mp3" server="siteground343.com/public_html/qasid.com/commons/" local="3608863357" remote="3602731980" Dst="-1" /><file name="B2090123v.mp3" server="siteground343.com/public_html/qasid.com/commons/" local="3608863358" remote="3602731980" Dst="-1" /></dwsync>