<?xml version="1.0" encoding="utf-8" ?><dwsync><file name="020401.mp3" server="siteground343.com/public_html/qasid.com/commons/" local="3608861666" remote="3577122000" Dst="-1" /><file name="020402.mp3" server="siteground343.com/public_html/qasid.com/commons/" local="3608861667" remote="3577122000" Dst="-1" /><file name="020403.mp3" server="siteground343.com/public_html/qasid.com/commons/" local="3608861668" remote="3577122000" Dst="-1" /><file name="020404.mp3" server="siteground343.com/public_html/qasid.com/commons/" local="3608861668" remote="3577122000" Dst="-1" /><file name="020405.mp3" server="siteground343.com/public_html/qasid.com/commons/" local="3608861669" remote="3577122000" Dst="-1" /><file name="020407.mp3" server="siteground343.com/public_html/qasid.com/commons/" local="3608861670" remote="3577122000" Dst="-1" /><file name="020406.mp3" server="siteground343.com/public_html/qasid.com/commons/" local="3608861670" remote="3577122000" Dst="-1" /><file name="020408.mp3" server="siteground343.com/public_html/qasid.com/commons/" local="3608861671" remote="3577122000" Dst="-1" /><file name="020409.mp3" server="siteground343.com/public_html/qasid.com/commons/" local="3608861680" remote="3577122000" Dst="-1" /></dwsync>