<?xml version="1.0" encoding="utf-8" ?><dwsync><file name="070401.mp3" server="siteground343.com/public_html/qasid.com/commons/" local="3608861915" remote="3578331600" Dst="-1" /><file name="070402.mp3" server="siteground343.com/public_html/qasid.com/commons/" local="3608861916" remote="3578331600" Dst="-1" /><file name="070403.mp3" server="siteground343.com/public_html/qasid.com/commons/" local="3608861916" remote="3578331600" Dst="-1" /><file name="070404.mp3" server="siteground343.com/public_html/qasid.com/commons/" local="3608861916" remote="3578331600" Dst="-1" /><file name="070405.mp3" server="siteground343.com/public_html/qasid.com/commons/" local="3608861916" remote="3578331600" Dst="-1" /><file name="070406.mp3" server="siteground343.com/public_html/qasid.com/commons/" local="3608861917" remote="3578331600" Dst="-1" /><file name="070407.mp3" server="siteground343.com/public_html/qasid.com/commons/" local="3608861917" remote="3578331600" Dst="-1" /><file name="070408.mp3" server="siteground343.com/public_html/qasid.com/commons/" local="3608861917" remote="3578331600" Dst="-1" /><file name="070409.mp3" server="siteground343.com/public_html/qasid.com/commons/" local="3608861918" remote="3578331600" Dst="-1" /><file name="070411.mp3" server="siteground343.com/public_html/qasid.com/commons/" local="3608861918" remote="3577294800" Dst="-1" /><file name="070410.mp3" server="siteground343.com/public_html/qasid.com/commons/" local="3608861918" remote="3578331600" Dst="-1" /></dwsync>